trees_ibm
