Metadata-Version: 1.0
Name: trees-ibm
Version: 0.2.2
Summary: Individual-based tree community models
Home-page: http://github.com/fsfrazao/Trees
Author: Fabio Frazao
Author-email: fsfrazao@gmail.com
License: GNU General Public License v3.0
Platform: UNKNOWN
